jupyterlab_hdf/__init__.py
jupyterlab_hdf/_version.py
jupyterlab_hdf/attrs.py
jupyterlab_hdf/baseHandler.py
jupyterlab_hdf/config.py
jupyterlab_hdf/contents.py
jupyterlab_hdf/data.py
jupyterlab_hdf/exception.py
jupyterlab_hdf/meta.py
jupyterlab_hdf/responses.py
jupyterlab_hdf/snippet.py
jupyterlab_hdf/util.py
jupyterlab_hdf-1.3.0.data/data/etc/jupyter/jupyter_notebook_config.d/jupyterlab_hdf.json
jupyterlab_hdf-1.3.0.dist-info/LICENSE
jupyterlab_hdf-1.3.0.dist-info/METADATA
jupyterlab_hdf-1.3.0.dist-info/WHEEL
jupyterlab_hdf-1.3.0.dist-info/top_level.txt
jupyterlab_hdf-1.3.0.dist-info/RECORD
