Metadata-Version: 2.1
Name: jupyterlab-hdf
Version: 1.3.0
Summary: A Jupyter Notebook server extension that provides APIs for fetching hdf5 contents and data. Built on h5py.
Home-page: https://github.com/telamonian/jupyterlab-hdf5
Author: Max Klein
License: BSD
Keywords: Jupyter,JupyterLab,hdf5
Platform: Linux
Platform: Mac OS X
Platform: Windows
Classifier: Intended Audience :: Developers
Classifier: Intended Audience :: System Administrators
Classifier: Intended Audience :: Science/Research
Classifier: License :: OSI Approved :: BSD License
Classifier: Programming Language :: Python
Classifier: Programming Language :: Python :: 3
Requires-Python: >=3.6
License-File: LICENSE
Requires-Dist: h5grove (==0.0.14)
Requires-Dist: h5py
Requires-Dist: notebook
Requires-Dist: numpy
Requires-Dist: tornado
Provides-Extra: dev
Requires-Dist: black ; extra == 'dev'
Requires-Dist: bump2version ; extra == 'dev'
Requires-Dist: pytest ; extra == 'dev'
Requires-Dist: requests ; extra == 'dev'
